qrc_pathlib/__init__.py
qrc_pathlib/pure_qrc_path.py
qrc_pathlib/qrc_glob.py
qrc_pathlib/qrc_path.py
qrc_pathlib/version.py
qrc_pathlib-1.0.2.dist-info/DESCRIPTION.rst
qrc_pathlib-1.0.2.dist-info/METADATA
qrc_pathlib-1.0.2.dist-info/RECORD
qrc_pathlib-1.0.2.dist-info/WHEEL
qrc_pathlib-1.0.2.dist-info/metadata.json
qrc_pathlib-1.0.2.dist-info/top_level.txt
