Metadata-Version: 2.0
Name: qrc-pathlib
Version: 1.0.2
Summary: Extension for pathlib that implements Path and PurePath for Qt Resources System.
Home-page: https://github.com/GreatFruitOmsk/qrc_pathlib
Author: Ilya Kulakov
Author-email: kulakov.ilya@gmail.com
License: MIT
Keywords: qt qrc pyqt pathlib
Platform: Mac OS X 10.6+
Platform: Windows XP+
Platform: Linux 2.6+
Classifier: Development Status :: 5 - Production/Stable
Classifier: Topic :: System :: Filesystems
Classifier: Intended Audience :: Developers
Classifier: License :: OSI Approved :: MIT License
Classifier: Natural Language :: English
Classifier: Operating System :: MacOS :: MacOS X
Classifier: Operating System :: Microsoft :: Windows
Classifier: Operating System :: POSIX :: Linux
Classifier: Programming Language :: Python
Classifier: Programming Language :: Python :: 3.4
Classifier: Programming Language :: Python :: 3.5
